crdp.cpython-313-darwin.so
crdp_gcr-0.1.dist-info/licenses/LICENSE.txt
crdp_gcr-0.1.dist-info/METADATA
crdp_gcr-0.1.dist-info/WHEEL
crdp_gcr-0.1.dist-info/top_level.txt
crdp_gcr-0.1.dist-info/RECORD
