Metadata-Version: 2.4
Name: crdp-gcr
Version: 0.1
Summary: A fast Ramer-Douglas-Peucker algorithm implementation. Updated for GCP cloud run
Home-page: https://github.com/vtecftwy/crdp-gcp
Author: Fabien PFAENDER
Author-email: fabien.pfaender@utc.fr
License: MIT
Keywords: rdp ramer douglas peucker line simplification cython
Classifier: Programming Language :: Python :: 3
Classifier: Operating System :: OS Independent
Requires-Python: >=3.10, <4
License-File: LICENSE.txt
Requires-Dist: cython
Provides-Extra: dev
Requires-Dist: cython; extra == "dev"
Dynamic: author
Dynamic: author-email
Dynamic: classifier
Dynamic: description
Dynamic: description-content-type
Dynamic: home-page
Dynamic: keywords
Dynamic: license
Dynamic: license-file
Dynamic: provides-extra
Dynamic: requires-dist
Dynamic: requires-python
Dynamic: summary
